{
  "generated_at": "2026-03-25 03:40:34",
  "source_model": "residual_ridge_pure_python",
  "items": [
    {
      "time": "2026-03-25 04:00:00",
      "date": "2026-03-25",
      "rule_expected_activity": 0.0,
      "ml_raw_residual_adjustment": 0.0,
      "ml_guarded_residual_adjustment": 0.0,
      "ml_residual_adjustment": 0.0,
      "ml_adjusted_activity": 0.0,
      "ml_confidence_scale": 0.7778,
      "ml_adjustment_cap": 0.08
    },
    {
      "time": "2026-03-25 05:00:00",
      "date": "2026-03-25",
      "rule_expected_activity": 0.0,
      "ml_raw_residual_adjustment": 0.0,
      "ml_guarded_residual_adjustment": 0.0,
      "ml_residual_adjustment": 0.0,
      "ml_adjusted_activity": 0.0,
      "ml_confidence_scale": 0.7778,
      "ml_adjustment_cap": 0.08
    },
    {
      "time": "2026-03-25 06:00:00",
      "date": "2026-03-25",
      "rule_expected_activity": 0.0117,
      "ml_raw_residual_adjustment": 0.0,
      "ml_guarded_residual_adjustment": 0.0,
      "ml_residual_adjustment": 0.0,
      "ml_adjusted_activity": 0.0117,
      "ml_confidence_scale": 0.7778,
      "ml_adjustment_cap": 0.08
    },
    {
      "time": "2026-03-25 07:00:00",
      "date": "2026-03-25",
      "rule_expected_activity": 0.0344,
      "ml_raw_residual_adjustment": 0.0,
      "ml_guarded_residual_adjustment": 0.0,
      "ml_residual_adjustment": 0.0,
      "ml_adjusted_activity": 0.0344,
      "ml_confidence_scale": 0.7778,
      "ml_adjustment_cap": 0.08
    },
    {
      "time": "2026-03-25 08:00:00",
      "date": "2026-03-25",
      "rule_expected_activity": 0.0859,
      "ml_raw_residual_adjustment": 0.2552,
      "ml_guarded_residual_adjustment": 0.08,
      "ml_residual_adjustment": 0.08,
      "ml_adjusted_activity": 0.1659,
      "ml_confidence_scale": 0.7778,
      "ml_adjustment_cap": 0.08
    },
    {
      "time": "2026-03-25 09:00:00",
      "date": "2026-03-25",
      "rule_expected_activity": 0.2267,
      "ml_raw_residual_adjustment": 0.0042,
      "ml_guarded_residual_adjustment": 0.0032,
      "ml_residual_adjustment": 0.0032,
      "ml_adjusted_activity": 0.2299,
      "ml_confidence_scale": 0.7778,
      "ml_adjustment_cap": 0.08
    },
    {
      "time": "2026-03-25 10:00:00",
      "date": "2026-03-25",
      "rule_expected_activity": 0.4157,
      "ml_raw_residual_adjustment": -0.1265,
      "ml_guarded_residual_adjustment": -0.08,
      "ml_residual_adjustment": -0.08,
      "ml_adjusted_activity": 0.3357,
      "ml_confidence_scale": 0.7778,
      "ml_adjustment_cap": 0.08
    },
    {
      "time": "2026-03-25 11:00:00",
      "date": "2026-03-25",
      "rule_expected_activity": 0.6305,
      "ml_raw_residual_adjustment": -0.2289,
      "ml_guarded_residual_adjustment": -0.08,
      "ml_residual_adjustment": -0.08,
      "ml_adjusted_activity": 0.5505,
      "ml_confidence_scale": 0.7778,
      "ml_adjustment_cap": 0.08
    },
    {
      "time": "2026-03-25 12:00:00",
      "date": "2026-03-25",
      "rule_expected_activity": 0.8096,
      "ml_raw_residual_adjustment": -0.3,
      "ml_guarded_residual_adjustment": -0.08,
      "ml_residual_adjustment": -0.08,
      "ml_adjusted_activity": 0.7296,
      "ml_confidence_scale": 0.7778,
      "ml_adjustment_cap": 0.08
    },
    {
      "time": "2026-03-25 13:00:00",
      "date": "2026-03-25",
      "rule_expected_activity": 0.88,
      "ml_raw_residual_adjustment": -0.3066,
      "ml_guarded_residual_adjustment": -0.08,
      "ml_residual_adjustment": -0.08,
      "ml_adjusted_activity": 0.8,
      "ml_confidence_scale": 0.7778,
      "ml_adjustment_cap": 0.08
    },
    {
      "time": "2026-03-25 14:00:00",
      "date": "2026-03-25",
      "rule_expected_activity": 0.8096,
      "ml_raw_residual_adjustment": -0.2925,
      "ml_guarded_residual_adjustment": -0.08,
      "ml_residual_adjustment": -0.08,
      "ml_adjusted_activity": 0.7296,
      "ml_confidence_scale": 0.7778,
      "ml_adjustment_cap": 0.08
    },
    {
      "time": "2026-03-25 15:00:00",
      "date": "2026-03-25",
      "rule_expected_activity": 0.6305,
      "ml_raw_residual_adjustment": -0.2564,
      "ml_guarded_residual_adjustment": -0.08,
      "ml_residual_adjustment": -0.08,
      "ml_adjusted_activity": 0.5505,
      "ml_confidence_scale": 0.7778,
      "ml_adjustment_cap": 0.08
    },
    {
      "time": "2026-03-25 16:00:00",
      "date": "2026-03-25",
      "rule_expected_activity": 0.4157,
      "ml_raw_residual_adjustment": -0.1851,
      "ml_guarded_residual_adjustment": -0.08,
      "ml_residual_adjustment": -0.08,
      "ml_adjusted_activity": 0.3357,
      "ml_confidence_scale": 0.7778,
      "ml_adjustment_cap": 0.08
    },
    {
      "time": "2026-03-25 17:00:00",
      "date": "2026-03-25",
      "rule_expected_activity": 0.232,
      "ml_raw_residual_adjustment": -0.1184,
      "ml_guarded_residual_adjustment": -0.08,
      "ml_residual_adjustment": -0.08,
      "ml_adjusted_activity": 0.152,
      "ml_confidence_scale": 0.7778,
      "ml_adjustment_cap": 0.08
    },
    {
      "time": "2026-03-25 18:00:00",
      "date": "2026-03-25",
      "rule_expected_activity": 0.1096,
      "ml_raw_residual_adjustment": 0.0,
      "ml_guarded_residual_adjustment": 0.0,
      "ml_residual_adjustment": 0.0,
      "ml_adjusted_activity": 0.1096,
      "ml_confidence_scale": 0.7778,
      "ml_adjustment_cap": 0.08
    },
    {
      "time": "2026-03-25 19:00:00",
      "date": "2026-03-25",
      "rule_expected_activity": 0.0438,
      "ml_raw_residual_adjustment": 0.0,
      "ml_guarded_residual_adjustment": 0.0,
      "ml_residual_adjustment": 0.0,
      "ml_adjusted_activity": 0.0438,
      "ml_confidence_scale": 0.7778,
      "ml_adjustment_cap": 0.08
    },
    {
      "time": "2026-03-25 20:00:00",
      "date": "2026-03-25",
      "rule_expected_activity": 0.0,
      "ml_raw_residual_adjustment": 0.0,
      "ml_guarded_residual_adjustment": 0.0,
      "ml_residual_adjustment": 0.0,
      "ml_adjusted_activity": 0.0,
      "ml_confidence_scale": 0.7778,
      "ml_adjustment_cap": 0.08
    },
    {
      "time": "2026-03-25 21:00:00",
      "date": "2026-03-25",
      "rule_expected_activity": 0.0,
      "ml_raw_residual_adjustment": 0.0,
      "ml_guarded_residual_adjustment": 0.0,
      "ml_residual_adjustment": 0.0,
      "ml_adjusted_activity": 0.0,
      "ml_confidence_scale": 0.7778,
      "ml_adjustment_cap": 0.08
    },
    {
      "time": "2026-03-25 22:00:00",
      "date": "2026-03-25",
      "rule_expected_activity": 0.0,
      "ml_raw_residual_adjustment": 0.0,
      "ml_guarded_residual_adjustment": 0.0,
      "ml_residual_adjustment": 0.0,
      "ml_adjusted_activity": 0.0,
      "ml_confidence_scale": 0.7778,
      "ml_adjustment_cap": 0.08
    },
    {
      "time": "2026-03-25 23:00:00",
      "date": "2026-03-25",
      "rule_expected_activity": 0.0,
      "ml_raw_residual_adjustment": 0.0,
      "ml_guarded_residual_adjustment": 0.0,
      "ml_residual_adjustment": 0.0,
      "ml_adjusted_activity": 0.0,
      "ml_confidence_scale": 0.7778,
      "ml_adjustment_cap": 0.08
    },
    {
      "time": "2026-03-26 00:00:00",
      "date": "2026-03-26",
      "rule_expected_activity": 0.0,
      "ml_raw_residual_adjustment": 0.0,
      "ml_guarded_residual_adjustment": 0.0,
      "ml_residual_adjustment": 0.0,
      "ml_adjusted_activity": 0.0,
      "ml_confidence_scale": 0.7778,
      "ml_adjustment_cap": 0.08
    },
    {
      "time": "2026-03-26 01:00:00",
      "date": "2026-03-26",
      "rule_expected_activity": 0.0,
      "ml_raw_residual_adjustment": 0.0,
      "ml_guarded_residual_adjustment": 0.0,
      "ml_residual_adjustment": 0.0,
      "ml_adjusted_activity": 0.0,
      "ml_confidence_scale": 0.7778,
      "ml_adjustment_cap": 0.08
    },
    {
      "time": "2026-03-26 02:00:00",
      "date": "2026-03-26",
      "rule_expected_activity": 0.0,
      "ml_raw_residual_adjustment": 0.0,
      "ml_guarded_residual_adjustment": 0.0,
      "ml_residual_adjustment": 0.0,
      "ml_adjusted_activity": 0.0,
      "ml_confidence_scale": 0.7778,
      "ml_adjustment_cap": 0.08
    },
    {
      "time": "2026-03-26 03:00:00",
      "date": "2026-03-26",
      "rule_expected_activity": 0.0,
      "ml_raw_residual_adjustment": 0.0,
      "ml_guarded_residual_adjustment": 0.0,
      "ml_residual_adjustment": 0.0,
      "ml_adjusted_activity": 0.0,
      "ml_confidence_scale": 0.7778,
      "ml_adjustment_cap": 0.08
    },
    {
      "time": "2026-03-26 04:00:00",
      "date": "2026-03-26",
      "rule_expected_activity": 0.0,
      "ml_raw_residual_adjustment": 0.0,
      "ml_guarded_residual_adjustment": 0.0,
      "ml_residual_adjustment": 0.0,
      "ml_adjusted_activity": 0.0,
      "ml_confidence_scale": 0.7778,
      "ml_adjustment_cap": 0.08
    },
    {
      "time": "2026-03-26 05:00:00",
      "date": "2026-03-26",
      "rule_expected_activity": 0.0,
      "ml_raw_residual_adjustment": 0.0,
      "ml_guarded_residual_adjustment": 0.0,
      "ml_residual_adjustment": 0.0,
      "ml_adjusted_activity": 0.0,
      "ml_confidence_scale": 0.7778,
      "ml_adjustment_cap": 0.08
    },
    {
      "time": "2026-03-26 06:00:00",
      "date": "2026-03-26",
      "rule_expected_activity": 0.0125,
      "ml_raw_residual_adjustment": 0.0,
      "ml_guarded_residual_adjustment": 0.0,
      "ml_residual_adjustment": 0.0,
      "ml_adjusted_activity": 0.0125,
      "ml_confidence_scale": 0.7778,
      "ml_adjustment_cap": 0.08
    },
    {
      "time": "2026-03-26 07:00:00",
      "date": "2026-03-26",
      "rule_expected_activity": 0.0438,
      "ml_raw_residual_adjustment": 0.0,
      "ml_guarded_residual_adjustment": 0.0,
      "ml_residual_adjustment": 0.0,
      "ml_adjusted_activity": 0.0438,
      "ml_confidence_scale": 0.7778,
      "ml_adjustment_cap": 0.08
    },
    {
      "time": "2026-03-26 08:00:00",
      "date": "2026-03-26",
      "rule_expected_activity": 0.1096,
      "ml_raw_residual_adjustment": -0.0867,
      "ml_guarded_residual_adjustment": -0.0674,
      "ml_residual_adjustment": -0.0674,
      "ml_adjusted_activity": 0.0422,
      "ml_confidence_scale": 0.7778,
      "ml_adjustment_cap": 0.08
    },
    {
      "time": "2026-03-26 09:00:00",
      "date": "2026-03-26",
      "rule_expected_activity": 0.232,
      "ml_raw_residual_adjustment": -0.132,
      "ml_guarded_residual_adjustment": -0.08,
      "ml_residual_adjustment": -0.08,
      "ml_adjusted_activity": 0.152,
      "ml_confidence_scale": 0.7778,
      "ml_adjustment_cap": 0.08
    },
    {
      "time": "2026-03-26 10:00:00",
      "date": "2026-03-26",
      "rule_expected_activity": 0.4157,
      "ml_raw_residual_adjustment": -0.1903,
      "ml_guarded_residual_adjustment": -0.08,
      "ml_residual_adjustment": -0.08,
      "ml_adjusted_activity": 0.3357,
      "ml_confidence_scale": 0.7778,
      "ml_adjustment_cap": 0.08
    },
    {
      "time": "2026-03-26 11:00:00",
      "date": "2026-03-26",
      "rule_expected_activity": 0.6592,
      "ml_raw_residual_adjustment": -0.4398,
      "ml_guarded_residual_adjustment": -0.08,
      "ml_residual_adjustment": -0.08,
      "ml_adjusted_activity": 0.5792,
      "ml_confidence_scale": 0.7778,
      "ml_adjustment_cap": 0.08
    }
  ]
}