{
  "generated_at": "2026-03-24 03:37:35",
  "model": {
    "target_layer": "第3层",
    "target_name": "蜜蜂行为模型",
    "ml_role": "残差修正",
    "model_type": "residual_ridge_pure_python",
    "trained_at": "2026-03-24 03:37:34",
    "sample_count": 52,
    "safeguards": {
      "full_confidence_sample_count": 72,
      "low_sample_cap": 0.04,
      "medium_sample_cap": 0.08,
      "high_sample_cap": 0.1
    }
  },
  "metrics": {
    "trained_at": "2026-03-24 03:37:34",
    "sample_count": 52,
    "timestamps": [
      "2026-03-10 14:00:00",
      "2026-03-10 15:00:00",
      "2026-03-11 13:00:00",
      "2026-03-11 14:00:00",
      "2026-03-11 15:00:00",
      "2026-03-12 12:00:00",
      "2026-03-12 13:00:00",
      "2026-03-12 14:00:00",
      "2026-03-12 15:00:00",
      "2026-03-12 16:00:00",
      "2026-03-12 17:00:00",
      "2026-03-13 09:00:00",
      "2026-03-13 10:00:00",
      "2026-03-13 11:00:00",
      "2026-03-13 12:00:00",
      "2026-03-13 13:00:00",
      "2026-03-13 14:00:00",
      "2026-03-13 16:00:00",
      "2026-03-13 17:00:00",
      "2026-03-14 14:00:00",
      "2026-03-14 15:00:00",
      "2026-03-14 16:00:00",
      "2026-03-14 17:00:00",
      "2026-03-15 12:00:00",
      "2026-03-15 14:00:00",
      "2026-03-15 15:00:00",
      "2026-03-15 16:00:00",
      "2026-03-15 17:00:00",
      "2026-03-16 13:00:00",
      "2026-03-16 14:00:00",
      "2026-03-16 15:00:00",
      "2026-03-16 16:00:00",
      "2026-03-17 13:00:00",
      "2026-03-17 14:00:00",
      "2026-03-18 12:00:00",
      "2026-03-18 13:00:00",
      "2026-03-18 14:00:00",
      "2026-03-18 15:00:00",
      "2026-03-18 16:00:00",
      "2026-03-18 17:00:00",
      "2026-03-19 13:00:00",
      "2026-03-19 14:00:00",
      "2026-03-19 15:00:00",
      "2026-03-20 13:00:00",
      "2026-03-20 14:00:00",
      "2026-03-20 15:00:00",
      "2026-03-20 17:00:00",
      "2026-03-23 12:00:00",
      "2026-03-23 13:00:00",
      "2026-03-23 14:00:00",
      "2026-03-23 15:00:00",
      "2026-03-23 16:00:00"
    ],
    "residual_metrics": {
      "mae": 0.0978,
      "rmse": 0.1321,
      "r2": 0.3472
    },
    "adjusted_activity_metrics": {
      "mae": 0.0978,
      "rmse": 0.1321,
      "r2": 0.4934
    }
  },
  "history": {
    "items": [
      {
        "time": "2026-03-10 14:00:00",
        "date": "2026-03-10",
        "actual_activity": 0.3777,
        "rule_expected_activity": 0.3946,
        "ml_adjusted_activity": 0.4087,
        "ml_raw_residual_adjustment": 0.0196,
        "ml_guarded_residual_adjustment": 0.0141,
        "ml_residual_adjustment": 0.0141,
        "ml_confidence_scale": 0.7222,
        "ml_adjustment_cap": 0.08,
        "rule_error": -0.0169,
        "ml_error": -0.031
      },
      {
        "time": "2026-03-10 15:00:00",
        "date": "2026-03-10",
        "actual_activity": 0.3707,
        "rule_expected_activity": 0.3073,
        "ml_adjusted_activity": 0.308,
        "ml_raw_residual_adjustment": 0.001,
        "ml_guarded_residual_adjustment": 0.0007,
        "ml_residual_adjustment": 0.0007,
        "ml_confidence_scale": 0.7222,
        "ml_adjustment_cap": 0.08,
        "rule_error": 0.0634,
        "ml_error": 0.0627
      },
      {
        "time": "2026-03-11 13:00:00",
        "date": "2026-03-11",
        "actual_activity": 0.5113,
        "rule_expected_activity": 0.5203,
        "ml_adjusted_activity": 0.4929,
        "ml_raw_residual_adjustment": -0.0379,
        "ml_guarded_residual_adjustment": -0.0274,
        "ml_residual_adjustment": -0.0274,
        "ml_confidence_scale": 0.7222,
        "ml_adjustment_cap": 0.08,
        "rule_error": -0.009,
        "ml_error": 0.0184
      },
      {
        "time": "2026-03-11 14:00:00",
        "date": "2026-03-11",
        "actual_activity": 0.3545,
        "rule_expected_activity": 0.4286,
        "ml_adjusted_activity": 0.4023,
        "ml_raw_residual_adjustment": -0.0365,
        "ml_guarded_residual_adjustment": -0.0263,
        "ml_residual_adjustment": -0.0263,
        "ml_confidence_scale": 0.7222,
        "ml_adjustment_cap": 0.08,
        "rule_error": -0.0741,
        "ml_error": -0.0478
      },
      {
        "time": "2026-03-11 15:00:00",
        "date": "2026-03-11",
        "actual_activity": 0.3066,
        "rule_expected_activity": 0.3338,
        "ml_adjusted_activity": 0.313,
        "ml_raw_residual_adjustment": -0.0289,
        "ml_guarded_residual_adjustment": -0.0208,
        "ml_residual_adjustment": -0.0208,
        "ml_confidence_scale": 0.7222,
        "ml_adjustment_cap": 0.08,
        "rule_error": -0.0272,
        "ml_error": -0.0064
      },
      {
        "time": "2026-03-12 12:00:00",
        "date": "2026-03-12",
        "actual_activity": 0.4928,
        "rule_expected_activity": 0.4787,
        "ml_adjusted_activity": 0.4683,
        "ml_raw_residual_adjustment": -0.0144,
        "ml_guarded_residual_adjustment": -0.0104,
        "ml_residual_adjustment": -0.0104,
        "ml_confidence_scale": 0.7222,
        "ml_adjustment_cap": 0.08,
        "rule_error": 0.0141,
        "ml_error": 0.0245
      },
      {
        "time": "2026-03-12 13:00:00",
        "date": "2026-03-12",
        "actual_activity": 0.5872,
        "rule_expected_activity": 0.5203,
        "ml_adjusted_activity": 0.4958,
        "ml_raw_residual_adjustment": -0.0339,
        "ml_guarded_residual_adjustment": -0.0245,
        "ml_residual_adjustment": -0.0245,
        "ml_confidence_scale": 0.7222,
        "ml_adjustment_cap": 0.08,
        "rule_error": 0.0669,
        "ml_error": 0.0914
      },
      {
        "time": "2026-03-12 14:00:00",
        "date": "2026-03-12",
        "actual_activity": 0.3582,
        "rule_expected_activity": 0.4787,
        "ml_adjusted_activity": 0.4526,
        "ml_raw_residual_adjustment": -0.0361,
        "ml_guarded_residual_adjustment": -0.0261,
        "ml_residual_adjustment": -0.0261,
        "ml_confidence_scale": 0.7222,
        "ml_adjustment_cap": 0.08,
        "rule_error": -0.1205,
        "ml_error": -0.0944
      },
      {
        "time": "2026-03-12 15:00:00",
        "date": "2026-03-12",
        "actual_activity": 0.2901,
        "rule_expected_activity": 0.3728,
        "ml_adjusted_activity": 0.3501,
        "ml_raw_residual_adjustment": -0.0315,
        "ml_guarded_residual_adjustment": -0.0227,
        "ml_residual_adjustment": -0.0227,
        "ml_confidence_scale": 0.7222,
        "ml_adjustment_cap": 0.08,
        "rule_error": -0.0827,
        "ml_error": -0.06
      },
      {
        "time": "2026-03-12 16:00:00",
        "date": "2026-03-12",
        "actual_activity": 0.27,
        "rule_expected_activity": 0.2458,
        "ml_adjusted_activity": 0.2433,
        "ml_raw_residual_adjustment": -0.0034,
        "ml_guarded_residual_adjustment": -0.0025,
        "ml_residual_adjustment": -0.0025,
        "ml_confidence_scale": 0.7222,
        "ml_adjustment_cap": 0.08,
        "rule_error": 0.0242,
        "ml_error": 0.0267
      },
      {
        "time": "2026-03-12 17:00:00",
        "date": "2026-03-12",
        "actual_activity": 0.1206,
        "rule_expected_activity": 0.1372,
        "ml_adjusted_activity": 0.1491,
        "ml_raw_residual_adjustment": 0.0165,
        "ml_guarded_residual_adjustment": 0.0119,
        "ml_residual_adjustment": 0.0119,
        "ml_confidence_scale": 0.7222,
        "ml_adjustment_cap": 0.08,
        "rule_error": -0.0166,
        "ml_error": -0.0285
      },
      {
        "time": "2026-03-13 09:00:00",
        "date": "2026-03-13",
        "actual_activity": 0.2849,
        "rule_expected_activity": 0.1014,
        "ml_adjusted_activity": 0.1814,
        "ml_raw_residual_adjustment": 0.2514,
        "ml_guarded_residual_adjustment": 0.08,
        "ml_residual_adjustment": 0.08,
        "ml_confidence_scale": 0.7222,
        "ml_adjustment_cap": 0.08,
        "rule_error": 0.1835,
        "ml_error": 0.1035
      },
      {
        "time": "2026-03-13 10:00:00",
        "date": "2026-03-13",
        "actual_activity": 0.4057,
        "rule_expected_activity": 0.2168,
        "ml_adjusted_activity": 0.2968,
        "ml_raw_residual_adjustment": 0.1426,
        "ml_guarded_residual_adjustment": 0.08,
        "ml_residual_adjustment": 0.08,
        "ml_confidence_scale": 0.7222,
        "ml_adjustment_cap": 0.08,
        "rule_error": 0.1889,
        "ml_error": 0.1089
      },
      {
        "time": "2026-03-13 11:00:00",
        "date": "2026-03-13",
        "actual_activity": 0.5752,
        "rule_expected_activity": 0.3288,
        "ml_adjusted_activity": 0.4088,
        "ml_raw_residual_adjustment": 0.1253,
        "ml_guarded_residual_adjustment": 0.08,
        "ml_residual_adjustment": 0.08,
        "ml_confidence_scale": 0.7222,
        "ml_adjustment_cap": 0.08,
        "rule_error": 0.2464,
        "ml_error": 0.1664
      },
      {
        "time": "2026-03-13 12:00:00",
        "date": "2026-03-13",
        "actual_activity": 0.4997,
        "rule_expected_activity": 0.5021,
        "ml_adjusted_activity": 0.5286,
        "ml_raw_residual_adjustment": 0.0366,
        "ml_guarded_residual_adjustment": 0.0265,
        "ml_residual_adjustment": 0.0265,
        "ml_confidence_scale": 0.7222,
        "ml_adjustment_cap": 0.08,
        "rule_error": -0.0024,
        "ml_error": -0.0289
      },
      {
        "time": "2026-03-13 13:00:00",
        "date": "2026-03-13",
        "actual_activity": 0.3773,
        "rule_expected_activity": 0.5334,
        "ml_adjusted_activity": 0.545,
        "ml_raw_residual_adjustment": 0.0161,
        "ml_guarded_residual_adjustment": 0.0116,
        "ml_residual_adjustment": 0.0116,
        "ml_confidence_scale": 0.7222,
        "ml_adjustment_cap": 0.08,
        "rule_error": -0.1561,
        "ml_error": -0.1677
      },
      {
        "time": "2026-03-13 14:00:00",
        "date": "2026-03-13",
        "actual_activity": 0.4048,
        "rule_expected_activity": 0.4907,
        "ml_adjusted_activity": 0.5143,
        "ml_raw_residual_adjustment": 0.0326,
        "ml_guarded_residual_adjustment": 0.0236,
        "ml_residual_adjustment": 0.0236,
        "ml_confidence_scale": 0.7222,
        "ml_adjustment_cap": 0.08,
        "rule_error": -0.0859,
        "ml_error": -0.1095
      },
      {
        "time": "2026-03-13 16:00:00",
        "date": "2026-03-13",
        "actual_activity": 0.4953,
        "rule_expected_activity": 0.2402,
        "ml_adjusted_activity": 0.2631,
        "ml_raw_residual_adjustment": 0.0317,
        "ml_guarded_residual_adjustment": 0.0229,
        "ml_residual_adjustment": 0.0229,
        "ml_confidence_scale": 0.7222,
        "ml_adjustment_cap": 0.08,
        "rule_error": 0.2551,
        "ml_error": 0.2322
      },
      {
        "time": "2026-03-13 17:00:00",
        "date": "2026-03-13",
        "actual_activity": 0.1962,
        "rule_expected_activity": 0.1341,
        "ml_adjusted_activity": 0.1644,
        "ml_raw_residual_adjustment": 0.0419,
        "ml_guarded_residual_adjustment": 0.0303,
        "ml_residual_adjustment": 0.0303,
        "ml_confidence_scale": 0.7222,
        "ml_adjustment_cap": 0.08,
        "rule_error": 0.0621,
        "ml_error": 0.0318
      },
      {
        "time": "2026-03-14 14:00:00",
        "date": "2026-03-14",
        "actual_activity": 0.2711,
        "rule_expected_activity": 0.4964,
        "ml_adjusted_activity": 0.4918,
        "ml_raw_residual_adjustment": -0.0064,
        "ml_guarded_residual_adjustment": -0.0046,
        "ml_residual_adjustment": -0.0046,
        "ml_confidence_scale": 0.7222,
        "ml_adjustment_cap": 0.08,
        "rule_error": -0.2253,
        "ml_error": -0.2207
      },
      {
        "time": "2026-03-14 15:00:00",
        "date": "2026-03-14",
        "actual_activity": 0.4727,
        "rule_expected_activity": 0.3866,
        "ml_adjusted_activity": 0.3651,
        "ml_raw_residual_adjustment": -0.0297,
        "ml_guarded_residual_adjustment": -0.0215,
        "ml_residual_adjustment": -0.0215,
        "ml_confidence_scale": 0.7222,
        "ml_adjustment_cap": 0.08,
        "rule_error": 0.0861,
        "ml_error": 0.1076
      },
      {
        "time": "2026-03-14 16:00:00",
        "date": "2026-03-14",
        "actual_activity": 0.2255,
        "rule_expected_activity": 0.2549,
        "ml_adjusted_activity": 0.2438,
        "ml_raw_residual_adjustment": -0.0153,
        "ml_guarded_residual_adjustment": -0.0111,
        "ml_residual_adjustment": -0.0111,
        "ml_confidence_scale": 0.7222,
        "ml_adjustment_cap": 0.08,
        "rule_error": -0.0294,
        "ml_error": -0.0183
      },
      {
        "time": "2026-03-14 17:00:00",
        "date": "2026-03-14",
        "actual_activity": 0.2004,
        "rule_expected_activity": 0.1259,
        "ml_adjusted_activity": 0.1649,
        "ml_raw_residual_adjustment": 0.0541,
        "ml_guarded_residual_adjustment": 0.039,
        "ml_residual_adjustment": 0.039,
        "ml_confidence_scale": 0.7222,
        "ml_adjustment_cap": 0.08,
        "rule_error": 0.0745,
        "ml_error": 0.0355
      },
      {
        "time": "2026-03-15 12:00:00",
        "date": "2026-03-15",
        "actual_activity": 0.5348,
        "rule_expected_activity": 0.4978,
        "ml_adjusted_activity": 0.5098,
        "ml_raw_residual_adjustment": 0.0166,
        "ml_guarded_residual_adjustment": 0.012,
        "ml_residual_adjustment": 0.012,
        "ml_confidence_scale": 0.7222,
        "ml_adjustment_cap": 0.08,
        "rule_error": 0.037,
        "ml_error": 0.025
      },
      {
        "time": "2026-03-15 14:00:00",
        "date": "2026-03-15",
        "actual_activity": 0.9535,
        "rule_expected_activity": 0.4978,
        "ml_adjusted_activity": 0.5502,
        "ml_raw_residual_adjustment": 0.0726,
        "ml_guarded_residual_adjustment": 0.0524,
        "ml_residual_adjustment": 0.0524,
        "ml_confidence_scale": 0.7222,
        "ml_adjustment_cap": 0.08,
        "rule_error": 0.4557,
        "ml_error": 0.4033
      },
      {
        "time": "2026-03-15 15:00:00",
        "date": "2026-03-15",
        "actual_activity": 0.5474,
        "rule_expected_activity": 0.3877,
        "ml_adjusted_activity": 0.4436,
        "ml_raw_residual_adjustment": 0.0774,
        "ml_guarded_residual_adjustment": 0.0559,
        "ml_residual_adjustment": 0.0559,
        "ml_confidence_scale": 0.7222,
        "ml_adjustment_cap": 0.08,
        "rule_error": 0.1597,
        "ml_error": 0.1038
      },
      {
        "time": "2026-03-15 16:00:00",
        "date": "2026-03-15",
        "actual_activity": 0.2881,
        "rule_expected_activity": 0.2556,
        "ml_adjusted_activity": 0.3143,
        "ml_raw_residual_adjustment": 0.0812,
        "ml_guarded_residual_adjustment": 0.0587,
        "ml_residual_adjustment": 0.0587,
        "ml_confidence_scale": 0.7222,
        "ml_adjustment_cap": 0.08,
        "rule_error": 0.0325,
        "ml_error": -0.0262
      },
      {
        "time": "2026-03-15 17:00:00",
        "date": "2026-03-15",
        "actual_activity": 0.172,
        "rule_expected_activity": 0.1426,
        "ml_adjusted_activity": 0.2217,
        "ml_raw_residual_adjustment": 0.1095,
        "ml_guarded_residual_adjustment": 0.0791,
        "ml_residual_adjustment": 0.0791,
        "ml_confidence_scale": 0.7222,
        "ml_adjustment_cap": 0.08,
        "rule_error": 0.0294,
        "ml_error": -0.0497
      },
      {
        "time": "2026-03-16 13:00:00",
        "date": "2026-03-16",
        "actual_activity": 0.6789,
        "rule_expected_activity": 0.4849,
        "ml_adjusted_activity": 0.423,
        "ml_raw_residual_adjustment": -0.0858,
        "ml_guarded_residual_adjustment": -0.0619,
        "ml_residual_adjustment": -0.0619,
        "ml_confidence_scale": 0.7222,
        "ml_adjustment_cap": 0.08,
        "rule_error": 0.194,
        "ml_error": 0.2559
      },
      {
        "time": "2026-03-16 14:00:00",
        "date": "2026-03-16",
        "actual_activity": 0.3644,
        "rule_expected_activity": 0.4787,
        "ml_adjusted_activity": 0.5087,
        "ml_raw_residual_adjustment": 0.0415,
        "ml_guarded_residual_adjustment": 0.03,
        "ml_residual_adjustment": 0.03,
        "ml_confidence_scale": 0.7222,
        "ml_adjustment_cap": 0.08,
        "rule_error": -0.1143,
        "ml_error": -0.1443
      },
      {
        "time": "2026-03-16 15:00:00",
        "date": "2026-03-16",
        "actual_activity": 0.346,
        "rule_expected_activity": 0.3728,
        "ml_adjusted_activity": 0.417,
        "ml_raw_residual_adjustment": 0.0612,
        "ml_guarded_residual_adjustment": 0.0442,
        "ml_residual_adjustment": 0.0442,
        "ml_confidence_scale": 0.7222,
        "ml_adjustment_cap": 0.08,
        "rule_error": -0.0268,
        "ml_error": -0.071
      },
      {
        "time": "2026-03-16 16:00:00",
        "date": "2026-03-16",
        "actual_activity": 0.2656,
        "rule_expected_activity": 0.2458,
        "ml_adjusted_activity": 0.2865,
        "ml_raw_residual_adjustment": 0.0564,
        "ml_guarded_residual_adjustment": 0.0407,
        "ml_residual_adjustment": 0.0407,
        "ml_confidence_scale": 0.7222,
        "ml_adjustment_cap": 0.08,
        "rule_error": 0.0198,
        "ml_error": -0.0209
      },
      {
        "time": "2026-03-17 13:00:00",
        "date": "2026-03-17",
        "actual_activity": 0.4853,
        "rule_expected_activity": 0.5176,
        "ml_adjusted_activity": 0.5638,
        "ml_raw_residual_adjustment": 0.0639,
        "ml_guarded_residual_adjustment": 0.0462,
        "ml_residual_adjustment": 0.0462,
        "ml_confidence_scale": 0.7222,
        "ml_adjustment_cap": 0.08,
        "rule_error": -0.0323,
        "ml_error": -0.0785
      },
      {
        "time": "2026-03-17 14:00:00",
        "date": "2026-03-17",
        "actual_activity": 0.4853,
        "rule_expected_activity": 0.4762,
        "ml_adjusted_activity": 0.5251,
        "ml_raw_residual_adjustment": 0.0678,
        "ml_guarded_residual_adjustment": 0.0489,
        "ml_residual_adjustment": 0.0489,
        "ml_confidence_scale": 0.7222,
        "ml_adjustment_cap": 0.08,
        "rule_error": 0.0091,
        "ml_error": -0.0398
      },
      {
        "time": "2026-03-18 12:00:00",
        "date": "2026-03-18",
        "actual_activity": 0.3053,
        "rule_expected_activity": 0.2906,
        "ml_adjusted_activity": 0.3414,
        "ml_raw_residual_adjustment": 0.0704,
        "ml_guarded_residual_adjustment": 0.0508,
        "ml_residual_adjustment": 0.0508,
        "ml_confidence_scale": 0.7222,
        "ml_adjustment_cap": 0.08,
        "rule_error": 0.0147,
        "ml_error": -0.0361
      },
      {
        "time": "2026-03-18 13:00:00",
        "date": "2026-03-18",
        "actual_activity": 1.0,
        "rule_expected_activity": 0.3963,
        "ml_adjusted_activity": 0.4763,
        "ml_raw_residual_adjustment": 0.3338,
        "ml_guarded_residual_adjustment": 0.08,
        "ml_residual_adjustment": 0.08,
        "ml_confidence_scale": 0.7222,
        "ml_adjustment_cap": 0.08,
        "rule_error": 0.6037,
        "ml_error": 0.5237
      },
      {
        "time": "2026-03-18 14:00:00",
        "date": "2026-03-18",
        "actual_activity": 0.3934,
        "rule_expected_activity": 0.3329,
        "ml_adjusted_activity": 0.4129,
        "ml_raw_residual_adjustment": 0.2344,
        "ml_guarded_residual_adjustment": 0.08,
        "ml_residual_adjustment": 0.08,
        "ml_confidence_scale": 0.7222,
        "ml_adjustment_cap": 0.08,
        "rule_error": 0.0605,
        "ml_error": -0.0195
      },
      {
        "time": "2026-03-18 15:00:00",
        "date": "2026-03-18",
        "actual_activity": 0.2856,
        "rule_expected_activity": 0.2264,
        "ml_adjusted_activity": 0.2613,
        "ml_raw_residual_adjustment": 0.0483,
        "ml_guarded_residual_adjustment": 0.0349,
        "ml_residual_adjustment": 0.0349,
        "ml_confidence_scale": 0.7222,
        "ml_adjustment_cap": 0.08,
        "rule_error": 0.0592,
        "ml_error": 0.0243
      },
      {
        "time": "2026-03-18 16:00:00",
        "date": "2026-03-18",
        "actual_activity": 0.2822,
        "rule_expected_activity": 0.1492,
        "ml_adjusted_activity": 0.1642,
        "ml_raw_residual_adjustment": 0.0207,
        "ml_guarded_residual_adjustment": 0.015,
        "ml_residual_adjustment": 0.015,
        "ml_confidence_scale": 0.7222,
        "ml_adjustment_cap": 0.08,
        "rule_error": 0.133,
        "ml_error": 0.118
      },
      {
        "time": "2026-03-18 17:00:00",
        "date": "2026-03-18",
        "actual_activity": 0.1719,
        "rule_expected_activity": 0.0772,
        "ml_adjusted_activity": 0.1572,
        "ml_raw_residual_adjustment": 0.2493,
        "ml_guarded_residual_adjustment": 0.08,
        "ml_residual_adjustment": 0.08,
        "ml_confidence_scale": 0.7222,
        "ml_adjustment_cap": 0.08,
        "rule_error": 0.0947,
        "ml_error": 0.0147
      },
      {
        "time": "2026-03-19 13:00:00",
        "date": "2026-03-19",
        "actual_activity": 0.5086,
        "rule_expected_activity": 0.5298,
        "ml_adjusted_activity": 0.5589,
        "ml_raw_residual_adjustment": 0.0402,
        "ml_guarded_residual_adjustment": 0.0291,
        "ml_residual_adjustment": 0.0291,
        "ml_confidence_scale": 0.7222,
        "ml_adjustment_cap": 0.08,
        "rule_error": -0.0212,
        "ml_error": -0.0503
      },
      {
        "time": "2026-03-19 14:00:00",
        "date": "2026-03-19",
        "actual_activity": 0.4329,
        "rule_expected_activity": 0.4875,
        "ml_adjusted_activity": 0.5091,
        "ml_raw_residual_adjustment": 0.0299,
        "ml_guarded_residual_adjustment": 0.0216,
        "ml_residual_adjustment": 0.0216,
        "ml_confidence_scale": 0.7222,
        "ml_adjustment_cap": 0.08,
        "rule_error": -0.0546,
        "ml_error": -0.0762
      },
      {
        "time": "2026-03-19 15:00:00",
        "date": "2026-03-19",
        "actual_activity": 0.4303,
        "rule_expected_activity": 0.3796,
        "ml_adjusted_activity": 0.4114,
        "ml_raw_residual_adjustment": 0.044,
        "ml_guarded_residual_adjustment": 0.0318,
        "ml_residual_adjustment": 0.0318,
        "ml_confidence_scale": 0.7222,
        "ml_adjustment_cap": 0.08,
        "rule_error": 0.0507,
        "ml_error": 0.0189
      },
      {
        "time": "2026-03-20 13:00:00",
        "date": "2026-03-20",
        "actual_activity": 0.0522,
        "rule_expected_activity": 0.4849,
        "ml_adjusted_activity": 0.4049,
        "ml_raw_residual_adjustment": -0.1441,
        "ml_guarded_residual_adjustment": -0.08,
        "ml_residual_adjustment": -0.08,
        "ml_confidence_scale": 0.7222,
        "ml_adjustment_cap": 0.08,
        "rule_error": -0.4327,
        "ml_error": -0.3527
      },
      {
        "time": "2026-03-20 14:00:00",
        "date": "2026-03-20",
        "actual_activity": 0.3864,
        "rule_expected_activity": 0.4461,
        "ml_adjusted_activity": 0.3661,
        "ml_raw_residual_adjustment": -0.1232,
        "ml_guarded_residual_adjustment": -0.08,
        "ml_residual_adjustment": -0.08,
        "ml_confidence_scale": 0.7222,
        "ml_adjustment_cap": 0.08,
        "rule_error": -0.0597,
        "ml_error": 0.0203
      },
      {
        "time": "2026-03-20 15:00:00",
        "date": "2026-03-20",
        "actual_activity": 0.3411,
        "rule_expected_activity": 0.3728,
        "ml_adjusted_activity": 0.37,
        "ml_raw_residual_adjustment": -0.0038,
        "ml_guarded_residual_adjustment": -0.0028,
        "ml_residual_adjustment": -0.0028,
        "ml_confidence_scale": 0.7222,
        "ml_adjustment_cap": 0.08,
        "rule_error": -0.0317,
        "ml_error": -0.0289
      },
      {
        "time": "2026-03-20 17:00:00",
        "date": "2026-03-20",
        "actual_activity": 0.1253,
        "rule_expected_activity": 0.106,
        "ml_adjusted_activity": 0.1208,
        "ml_raw_residual_adjustment": 0.0205,
        "ml_guarded_residual_adjustment": 0.0148,
        "ml_residual_adjustment": 0.0148,
        "ml_confidence_scale": 0.7222,
        "ml_adjustment_cap": 0.08,
        "rule_error": 0.0193,
        "ml_error": 0.0045
      },
      {
        "time": "2026-03-23 12:00:00",
        "date": "2026-03-23",
        "actual_activity": 0.1529,
        "rule_expected_activity": 0.433,
        "ml_adjusted_activity": 0.3636,
        "ml_raw_residual_adjustment": -0.0961,
        "ml_guarded_residual_adjustment": -0.0694,
        "ml_residual_adjustment": -0.0694,
        "ml_confidence_scale": 0.7222,
        "ml_adjustment_cap": 0.08,
        "rule_error": -0.2801,
        "ml_error": -0.2107
      },
      {
        "time": "2026-03-23 13:00:00",
        "date": "2026-03-23",
        "actual_activity": 0.634,
        "rule_expected_activity": 0.4706,
        "ml_adjusted_activity": 0.4065,
        "ml_raw_residual_adjustment": -0.0888,
        "ml_guarded_residual_adjustment": -0.0641,
        "ml_residual_adjustment": -0.0641,
        "ml_confidence_scale": 0.7222,
        "ml_adjustment_cap": 0.08,
        "rule_error": 0.1634,
        "ml_error": 0.2275
      },
      {
        "time": "2026-03-23 14:00:00",
        "date": "2026-03-23",
        "actual_activity": 0.4124,
        "rule_expected_activity": 0.4224,
        "ml_adjusted_activity": 0.4111,
        "ml_raw_residual_adjustment": -0.0156,
        "ml_guarded_residual_adjustment": -0.0113,
        "ml_residual_adjustment": -0.0113,
        "ml_confidence_scale": 0.7222,
        "ml_adjustment_cap": 0.08,
        "rule_error": -0.01,
        "ml_error": 0.0013
      },
      {
        "time": "2026-03-23 15:00:00",
        "date": "2026-03-23",
        "actual_activity": 0.7183,
        "rule_expected_activity": 0.3536,
        "ml_adjusted_activity": 0.4307,
        "ml_raw_residual_adjustment": 0.1068,
        "ml_guarded_residual_adjustment": 0.0771,
        "ml_residual_adjustment": 0.0771,
        "ml_confidence_scale": 0.7222,
        "ml_adjustment_cap": 0.08,
        "rule_error": 0.3647,
        "ml_error": 0.2876
      },
      {
        "time": "2026-03-23 16:00:00",
        "date": "2026-03-23",
        "actual_activity": 0.282,
        "rule_expected_activity": 0.2332,
        "ml_adjusted_activity": 0.3132,
        "ml_raw_residual_adjustment": 0.1212,
        "ml_guarded_residual_adjustment": 0.08,
        "ml_residual_adjustment": 0.08,
        "ml_confidence_scale": 0.7222,
        "ml_adjustment_cap": 0.08,
        "rule_error": 0.0488,
        "ml_error": -0.0312
      }
    ],
    "summary": {
      "sample_count": 52,
      "rule_mae": 0.1101,
      "ml_mae": 0.0978,
      "mae_improvement": 0.0123
    }
  },
  "future": {
    "generated_at": "2026-03-24 03:37:35",
    "source_model": "residual_ridge_pure_python",
    "items": [
      {
        "time": "2026-03-24 04:00:00",
        "date": "2026-03-24",
        "rule_expected_activity": 0.0,
        "ml_raw_residual_adjustment": 0.0,
        "ml_guarded_residual_adjustment": 0.0,
        "ml_residual_adjustment": 0.0,
        "ml_adjusted_activity": 0.0,
        "ml_confidence_scale": 0.7222,
        "ml_adjustment_cap": 0.08
      },
      {
        "time": "2026-03-24 05:00:00",
        "date": "2026-03-24",
        "rule_expected_activity": 0.0,
        "ml_raw_residual_adjustment": 0.0,
        "ml_guarded_residual_adjustment": 0.0,
        "ml_residual_adjustment": 0.0,
        "ml_adjusted_activity": 0.0,
        "ml_confidence_scale": 0.7222,
        "ml_adjustment_cap": 0.08
      },
      {
        "time": "2026-03-24 06:00:00",
        "date": "2026-03-24",
        "rule_expected_activity": 0.0106,
        "ml_raw_residual_adjustment": 0.0,
        "ml_guarded_residual_adjustment": 0.0,
        "ml_residual_adjustment": 0.0,
        "ml_adjusted_activity": 0.0106,
        "ml_confidence_scale": 0.7222,
        "ml_adjustment_cap": 0.08
      },
      {
        "time": "2026-03-24 07:00:00",
        "date": "2026-03-24",
        "rule_expected_activity": 0.0344,
        "ml_raw_residual_adjustment": 0.0,
        "ml_guarded_residual_adjustment": 0.0,
        "ml_residual_adjustment": 0.0,
        "ml_adjusted_activity": 0.0344,
        "ml_confidence_scale": 0.7222,
        "ml_adjustment_cap": 0.08
      },
      {
        "time": "2026-03-24 08:00:00",
        "date": "2026-03-24",
        "rule_expected_activity": 0.0784,
        "ml_raw_residual_adjustment": 0.1132,
        "ml_guarded_residual_adjustment": 0.08,
        "ml_residual_adjustment": 0.08,
        "ml_adjusted_activity": 0.1584,
        "ml_confidence_scale": 0.7222,
        "ml_adjustment_cap": 0.08
      },
      {
        "time": "2026-03-24 09:00:00",
        "date": "2026-03-24",
        "rule_expected_activity": 0.145,
        "ml_raw_residual_adjustment": -0.1709,
        "ml_guarded_residual_adjustment": -0.08,
        "ml_residual_adjustment": -0.08,
        "ml_adjusted_activity": 0.065,
        "ml_confidence_scale": 0.7222,
        "ml_adjustment_cap": 0.08
      },
      {
        "time": "2026-03-24 10:00:00",
        "date": "2026-03-24",
        "rule_expected_activity": 0.326,
        "ml_raw_residual_adjustment": 0.1585,
        "ml_guarded_residual_adjustment": 0.08,
        "ml_residual_adjustment": 0.08,
        "ml_adjusted_activity": 0.406,
        "ml_confidence_scale": 0.7222,
        "ml_adjustment_cap": 0.08
      },
      {
        "time": "2026-03-24 11:00:00",
        "date": "2026-03-24",
        "rule_expected_activity": 0.5159,
        "ml_raw_residual_adjustment": 0.0039,
        "ml_guarded_residual_adjustment": 0.0028,
        "ml_residual_adjustment": 0.0028,
        "ml_adjusted_activity": 0.5187,
        "ml_confidence_scale": 0.7222,
        "ml_adjustment_cap": 0.08
      },
      {
        "time": "2026-03-24 12:00:00",
        "date": "2026-03-24",
        "rule_expected_activity": 0.5796,
        "ml_raw_residual_adjustment": -0.011,
        "ml_guarded_residual_adjustment": -0.0079,
        "ml_residual_adjustment": -0.0079,
        "ml_adjusted_activity": 0.5717,
        "ml_confidence_scale": 0.7222,
        "ml_adjustment_cap": 0.08
      },
      {
        "time": "2026-03-24 13:00:00",
        "date": "2026-03-24",
        "rule_expected_activity": 0.63,
        "ml_raw_residual_adjustment": -0.0049,
        "ml_guarded_residual_adjustment": -0.0035,
        "ml_residual_adjustment": -0.0035,
        "ml_adjusted_activity": 0.6265,
        "ml_confidence_scale": 0.7222,
        "ml_adjustment_cap": 0.08
      },
      {
        "time": "2026-03-24 14:00:00",
        "date": "2026-03-24",
        "rule_expected_activity": 0.5796,
        "ml_raw_residual_adjustment": 0.0154,
        "ml_guarded_residual_adjustment": 0.0111,
        "ml_residual_adjustment": 0.0111,
        "ml_adjusted_activity": 0.5907,
        "ml_confidence_scale": 0.7222,
        "ml_adjustment_cap": 0.08
      },
      {
        "time": "2026-03-24 15:00:00",
        "date": "2026-03-24",
        "rule_expected_activity": 0.4944,
        "ml_raw_residual_adjustment": 0.1444,
        "ml_guarded_residual_adjustment": 0.08,
        "ml_residual_adjustment": 0.08,
        "ml_adjusted_activity": 0.5744,
        "ml_confidence_scale": 0.7222,
        "ml_adjustment_cap": 0.08
      },
      {
        "time": "2026-03-24 16:00:00",
        "date": "2026-03-24",
        "rule_expected_activity": 0.2976,
        "ml_raw_residual_adjustment": 0.0916,
        "ml_guarded_residual_adjustment": 0.0661,
        "ml_residual_adjustment": 0.0661,
        "ml_adjusted_activity": 0.3637,
        "ml_confidence_scale": 0.7222,
        "ml_adjustment_cap": 0.08
      },
      {
        "time": "2026-03-24 17:00:00",
        "date": "2026-03-24",
        "rule_expected_activity": 0.1661,
        "ml_raw_residual_adjustment": 0.1209,
        "ml_guarded_residual_adjustment": 0.08,
        "ml_residual_adjustment": 0.08,
        "ml_adjusted_activity": 0.2461,
        "ml_confidence_scale": 0.7222,
        "ml_adjustment_cap": 0.08
      },
      {
        "time": "2026-03-24 18:00:00",
        "date": "2026-03-24",
        "rule_expected_activity": 0.0784,
        "ml_raw_residual_adjustment": 0.0,
        "ml_guarded_residual_adjustment": 0.0,
        "ml_residual_adjustment": 0.0,
        "ml_adjusted_activity": 0.0784,
        "ml_confidence_scale": 0.7222,
        "ml_adjustment_cap": 0.08
      },
      {
        "time": "2026-03-24 19:00:00",
        "date": "2026-03-24",
        "rule_expected_activity": 0.0314,
        "ml_raw_residual_adjustment": 0.0,
        "ml_guarded_residual_adjustment": 0.0,
        "ml_residual_adjustment": 0.0,
        "ml_adjusted_activity": 0.0314,
        "ml_confidence_scale": 0.7222,
        "ml_adjustment_cap": 0.08
      },
      {
        "time": "2026-03-24 20:00:00",
        "date": "2026-03-24",
        "rule_expected_activity": 0.0,
        "ml_raw_residual_adjustment": 0.0,
        "ml_guarded_residual_adjustment": 0.0,
        "ml_residual_adjustment": 0.0,
        "ml_adjusted_activity": 0.0,
        "ml_confidence_scale": 0.7222,
        "ml_adjustment_cap": 0.08
      },
      {
        "time": "2026-03-24 21:00:00",
        "date": "2026-03-24",
        "rule_expected_activity": 0.0,
        "ml_raw_residual_adjustment": 0.0,
        "ml_guarded_residual_adjustment": 0.0,
        "ml_residual_adjustment": 0.0,
        "ml_adjusted_activity": 0.0,
        "ml_confidence_scale": 0.7222,
        "ml_adjustment_cap": 0.08
      },
      {
        "time": "2026-03-24 22:00:00",
        "date": "2026-03-24",
        "rule_expected_activity": 0.0,
        "ml_raw_residual_adjustment": 0.0,
        "ml_guarded_residual_adjustment": 0.0,
        "ml_residual_adjustment": 0.0,
        "ml_adjusted_activity": 0.0,
        "ml_confidence_scale": 0.7222,
        "ml_adjustment_cap": 0.08
      },
      {
        "time": "2026-03-24 23:00:00",
        "date": "2026-03-24",
        "rule_expected_activity": 0.0,
        "ml_raw_residual_adjustment": 0.0,
        "ml_guarded_residual_adjustment": 0.0,
        "ml_residual_adjustment": 0.0,
        "ml_adjusted_activity": 0.0,
        "ml_confidence_scale": 0.7222,
        "ml_adjustment_cap": 0.08
      },
      {
        "time": "2026-03-25 00:00:00",
        "date": "2026-03-25",
        "rule_expected_activity": 0.0,
        "ml_raw_residual_adjustment": 0.0,
        "ml_guarded_residual_adjustment": 0.0,
        "ml_residual_adjustment": 0.0,
        "ml_adjusted_activity": 0.0,
        "ml_confidence_scale": 0.7222,
        "ml_adjustment_cap": 0.08
      },
      {
        "time": "2026-03-25 01:00:00",
        "date": "2026-03-25",
        "rule_expected_activity": 0.0,
        "ml_raw_residual_adjustment": 0.0,
        "ml_guarded_residual_adjustment": 0.0,
        "ml_residual_adjustment": 0.0,
        "ml_adjusted_activity": 0.0,
        "ml_confidence_scale": 0.7222,
        "ml_adjustment_cap": 0.08
      },
      {
        "time": "2026-03-25 02:00:00",
        "date": "2026-03-25",
        "rule_expected_activity": 0.0,
        "ml_raw_residual_adjustment": 0.0,
        "ml_guarded_residual_adjustment": 0.0,
        "ml_residual_adjustment": 0.0,
        "ml_adjusted_activity": 0.0,
        "ml_confidence_scale": 0.7222,
        "ml_adjustment_cap": 0.08
      },
      {
        "time": "2026-03-25 03:00:00",
        "date": "2026-03-25",
        "rule_expected_activity": 0.0,
        "ml_raw_residual_adjustment": 0.0,
        "ml_guarded_residual_adjustment": 0.0,
        "ml_residual_adjustment": 0.0,
        "ml_adjusted_activity": 0.0,
        "ml_confidence_scale": 0.7222,
        "ml_adjustment_cap": 0.08
      },
      {
        "time": "2026-03-25 04:00:00",
        "date": "2026-03-25",
        "rule_expected_activity": 0.0,
        "ml_raw_residual_adjustment": 0.0,
        "ml_guarded_residual_adjustment": 0.0,
        "ml_residual_adjustment": 0.0,
        "ml_adjusted_activity": 0.0,
        "ml_confidence_scale": 0.7222,
        "ml_adjustment_cap": 0.08
      },
      {
        "time": "2026-03-25 05:00:00",
        "date": "2026-03-25",
        "rule_expected_activity": 0.0,
        "ml_raw_residual_adjustment": 0.0,
        "ml_guarded_residual_adjustment": 0.0,
        "ml_residual_adjustment": 0.0,
        "ml_adjusted_activity": 0.0,
        "ml_confidence_scale": 0.7222,
        "ml_adjustment_cap": 0.08
      },
      {
        "time": "2026-03-25 06:00:00",
        "date": "2026-03-25",
        "rule_expected_activity": 0.0117,
        "ml_raw_residual_adjustment": 0.0,
        "ml_guarded_residual_adjustment": 0.0,
        "ml_residual_adjustment": 0.0,
        "ml_adjusted_activity": 0.0117,
        "ml_confidence_scale": 0.7222,
        "ml_adjustment_cap": 0.08
      },
      {
        "time": "2026-03-25 07:00:00",
        "date": "2026-03-25",
        "rule_expected_activity": 0.0344,
        "ml_raw_residual_adjustment": 0.0,
        "ml_guarded_residual_adjustment": 0.0,
        "ml_residual_adjustment": 0.0,
        "ml_adjusted_activity": 0.0344,
        "ml_confidence_scale": 0.7222,
        "ml_adjustment_cap": 0.08
      },
      {
        "time": "2026-03-25 08:00:00",
        "date": "2026-03-25",
        "rule_expected_activity": 0.0859,
        "ml_raw_residual_adjustment": 0.2887,
        "ml_guarded_residual_adjustment": 0.08,
        "ml_residual_adjustment": 0.08,
        "ml_adjusted_activity": 0.1659,
        "ml_confidence_scale": 0.7222,
        "ml_adjustment_cap": 0.08
      },
      {
        "time": "2026-03-25 09:00:00",
        "date": "2026-03-25",
        "rule_expected_activity": 0.2267,
        "ml_raw_residual_adjustment": 0.0307,
        "ml_guarded_residual_adjustment": 0.0222,
        "ml_residual_adjustment": 0.0222,
        "ml_adjusted_activity": 0.2489,
        "ml_confidence_scale": 0.7222,
        "ml_adjustment_cap": 0.08
      },
      {
        "time": "2026-03-25 10:00:00",
        "date": "2026-03-25",
        "rule_expected_activity": 0.4157,
        "ml_raw_residual_adjustment": -0.1009,
        "ml_guarded_residual_adjustment": -0.0729,
        "ml_residual_adjustment": -0.0729,
        "ml_adjusted_activity": 0.3428,
        "ml_confidence_scale": 0.7222,
        "ml_adjustment_cap": 0.08
      },
      {
        "time": "2026-03-25 11:00:00",
        "date": "2026-03-25",
        "rule_expected_activity": 0.6305,
        "ml_raw_residual_adjustment": -0.2021,
        "ml_guarded_residual_adjustment": -0.08,
        "ml_residual_adjustment": -0.08,
        "ml_adjusted_activity": 0.5505,
        "ml_confidence_scale": 0.7222,
        "ml_adjustment_cap": 0.08
      }
    ]
  },
  "alerts": [
    {
      "level": "warning",
      "title": "样本量偏少",
      "message": "当前仅有 52 条可训练样本，系统已自动缩小 ML 修正幅度，现阶段更适合作为辅助参考，而不是直接替代规则模型。"
    },
    {
      "level": "warning",
      "title": "未来修正触及保护上限",
      "message": "未来预测中的修正量已经触及当前保护上限 0.08，说明模型原始修正意图偏大，建议人工复核规则模型与样本质量。"
    }
  ]
}